main.py
mseep_whoami_mcp-0.1.4.dist-info/licenses/LICENSE
mseep_whoami_mcp-0.1.4.dist-info/METADATA
mseep_whoami_mcp-0.1.4.dist-info/WHEEL
mseep_whoami_mcp-0.1.4.dist-info/entry_points.txt
mseep_whoami_mcp-0.1.4.dist-info/top_level.txt
mseep_whoami_mcp-0.1.4.dist-info/RECORD
